owl_parser/__init__.py
owl_parser/bp/__init__.py
owl_parser/bp/mutato_api.py
owl_parser/dmo/__init__.py
owl_parser/dmo/core/__init__.py
owl_parser/dmo/core/swap_token_generator.py
owl_parser/dmo/exact/__init__.py
owl_parser/dmo/exact/sliding_window_blacklist.py
owl_parser/dmo/exact/sliding_window_extract.py
owl_parser/dmo/exact/sliding_window_lookup.py
owl_parser/dmo/exact_match_finder.py
owl_parser/dmo/exact_match_swapper.py
owl_parser/dmo/hierarchy_match_finder.py
owl_parser/dmo/hierarchy_match_swapper.py
owl_parser/dmo/spacy_match_finder.py
owl_parser/dmo/spacy_match_swapper.py
owl_parser/dmo/span_match_finder.py
owl_parser/dmo/span_match_swapper.py
owl_parser/dmo/spans/__init__.py
owl_parser/dmo/spans/span_content_check.py
owl_parser/dmo/spans/span_context_check.py
owl_parser/dmo/spans/span_distance_check.py
owl_parser/dmo/swap_result_summarizer.py
owl_parser/dto/__init__.py
owl_parser/dto/candidate_synonym_blacklist_kb.py
owl_parser/svc/__init__.py
owl_parser/svc/augment_token_hierarchy.py
owl_parser/svc/perform_exact_matching.py
owl_parser/svc/perform_hierarchy_matching.py
owl_parser/svc/perform_spacy_matching.py
owl_parser/svc/perform_span_matching.py
owl_parser-0.1.18.dist-info/WHEEL
owl_parser-0.1.18.dist-info/METADATA
owl_parser-0.1.18.dist-info/RECORD
