Metadata-Version: 2.1
Name: owl-parser
Version: 0.1.18
Summary: Parse Input Text using One-or-More Ontology (OWL) files
Home-page: https://github.com/craigtrim/owl-parser
License: None
Keywords: nlp,nlu,text,classify,classification
Author: Craig Trim
Author-email: craigtrim@gmail.com
Maintainer: Craig Trim
Maintainer-email: craigtrim@gmail.com
Requires-Python: >=3.8.5,<4.0.0
Classifier: Development Status :: 4 - Beta
Classifier: License :: Other/Proprietary License
Classifier: Programming Language :: Python :: 3
Classifier: Programming Language :: Python :: 3.10
Classifier: Programming Language :: Python :: 3.9
Classifier: Topic :: Software Development :: Libraries :: Python Modules
Requires-Dist: baseblock
Requires-Dist: owl-finder
Requires-Dist: rdflib (>=6.2.0,<7.0.0)
Requires-Dist: regression-framework
Project-URL: Bug Tracker, https://github.com/craigtrim/owl-parser/issues
Project-URL: Repository, https://github.com/craigtrim/owl-parser
